posit_playground/__init__.py
posit_playground/f64.py
posit_playground/posit.py
posit_playground/regime.py
posit_playground/utils.py
posit_playground-0.1.3.dist-info/WHEEL
posit_playground-0.1.3.dist-info/METADATA
posit_playground-0.1.3.dist-info/RECORD
