Metadata-Version: 2.1
Name: posit-playground
Version: 0.1.3
Summary: Posit arithmetic library with no frills
Home-page: https://github.com/urbanij/posit-playground
Keywords: posit,unum,posit-arithmetic,numeric-representation
Author: Francesco Urbani
Author-email: francescourbanidue@gmail.com
Requires-Python: >=3.6,<4.0
Classifier: Programming Language :: Python :: 3
Classifier: Programming Language :: Python :: 3.10
Classifier: Programming Language :: Python :: 3.6
Classifier: Programming Language :: Python :: 3.7
Classifier: Programming Language :: Python :: 3.8
Classifier: Programming Language :: Python :: 3.9
Requires-Dist: pytest (>=6.2.5,<7.0.0)
Requires-Dist: softposit (>=0.3.4.4,<0.4.0.0)
Project-URL: Repository, https://github.com/urbanij/posit-playground
